hv_bie/__init__.py
hv_bie/py.typed
hv_bie/snapshot.py
hv_bie/parsers/__init__.py
hv_bie/parsers/core.py
hv_bie/parsers/py.typed
hv_bie/types/__init__.py
hv_bie/types/models.py
hv_bie/types/py.typed
hv_bie/types/system_monsters.py
hv_bie-0.3.7.dist-info/licenses/LICENSE
hv_bie-0.3.7.dist-info/METADATA
hv_bie-0.3.7.dist-info/WHEEL
hv_bie-0.3.7.dist-info/top_level.txt
hv_bie-0.3.7.dist-info/RECORD
