Metadata-Version: 2.4
Name: hv_bie
Version: 0.3.7
Summary: HV Battle Intelligence Extractor: parse HentaiVerse battle HTML into structured Python dataclasses
Author-email: Kuan-Lun Wang <polyphonicared@gmail.com>
License-Expression: AGPL-3.0-or-later
Project-URL: Homepage, https://github.com/Kuan-Lun/hv-bie
Project-URL: Source, https://github.com/Kuan-Lun/hv-bie
Project-URL: Tracker, https://github.com/Kuan-Lun/hv-bie/issues
Classifier: Programming Language :: Python :: 3
Classifier: Programming Language :: Python :: 3.14
Classifier: Programming Language :: Python :: 3.13
Classifier: Programming Language :: Python :: 3.12
Classifier: Programming Language :: Python :: 3.10
Classifier: Programming Language :: Python :: 3.9
Classifier: Operating System :: OS Independent
Requires-Python: >=3.9
License-File: LICENSE
Requires-Dist: beautifulsoup4<5.0.0,>=4.14.2
Provides-Extra: dev
Requires-Dist: ruff<1.0.0,>=0.14.3; extra == "dev"
Requires-Dist: mypy<2.0.0,>=1.18.2; extra == "dev"
Requires-Dist: pytest<9.0.0,>=8.4.2; extra == "dev"
Requires-Dist: black>=23.9.1; extra == "dev"
Dynamic: license-file
